mcp_bigquery_dryrun/__init__.py
mcp_bigquery_dryrun/__main__.py
mcp_bigquery_dryrun/bigquery_client.py
mcp_bigquery_dryrun/server.py
mcp_bigquery_dryrun-0.2.0.dist-info/METADATA
mcp_bigquery_dryrun-0.2.0.dist-info/WHEEL
mcp_bigquery_dryrun-0.2.0.dist-info/entry_points.txt
mcp_bigquery_dryrun-0.2.0.dist-info/licenses/LICENSE
mcp_bigquery_dryrun-0.2.0.dist-info/RECORD
